[{"id":0,"meeting_name":"125  Two For One -","location_name":"Harlem Children's Zone Admin. Offices","meeting_address":"35 E 125 ST New York NY ","meeting_times":{"Monday":{"start":"","end":"","details":{"topic":"","interest":""}},"Tuesday":{"start":"","end":"","details":{"topic":"","interest":""}},"Wednesday":{"start":"","end":"","details":{"topic":"","interest":""}},"Thursday":{"start":"","end":"","details":{"topic":"","interest":""}},"Friday":{"start":"","end":"","details":{"topic":"","interest":""}},"Saturday":{"start":"4:15 PM","end":"5:30 PM","details":{"topic":"B = Beginners meeting","interest":""}},"Sunday":{"start":"4:15 PM","end":"5:30 PM","details":{"topic":"B = Beginners meeting","interest":""}}},"latlong":{"lat":"40.805958","lng":"-73.940763"}},{"id":1,"meeting_name":"East Harlem  East Harlem","location_name":"Peter Jay Sharpe Building","meeting_address":"223 E 117TH ST New York NY ","meeting_times":{"Monday":{"start":"","end":"","details":{"topic":"","interest":""}},"Tuesday":{"start":"6:30 PM","end":"7:30 PM","details":{"topic":"B = Beginners meeting","interest":"Living Sober"}},"Wednesday":{"start":"","end":"","details":{"topic":"","interest":""}},"Thursday":{"start":"","end":"","details":{"topic":"","interest":""}},"Friday":{"start":"","end":"","details":{"topic":"","interest":""}},"Saturday":{"start":"","end":"","details":{"topic":"","interest":""}},"Sunday":{"start":"","end":"","details":{"topic":"","interest":""}}},"latlong":{"lat":"40.7982106","lng":"-73.9382769"}},{"id":2,"meeting_name":"Grupo Nueva Vida  Grupo Nueva Vida","location_name":"","meeting_address":"2126 2ND AVE New York NY ","meeting_times":{"Monday":{"start":"8:00 PM","end":"9:00 PM","details":{"topic":"B = Beginners meeting","interest":""}},"Tuesday":{"start":"8:00 PM","end":"9:00 PM","details":{"topic":"OD = Open Discussion meeting","interest":""}},"Wednesday":{"start":"8:00 PM","end":"9:00 PM","details":{"topic":"C = Closed Discussion meeting","interest":""}},"Thursday":{"start":"8:00 PM","end":"9:00 PM","details":{"topic":"OD = Open Discussion meeting","interest":""}},"Friday":{"start":"8:00 PM","end":"9:00 PM","details":{"topic":"OD = Open Discussion meeting","interest":""}},"Saturday":{"start":"8:00 PM","end":"9:00 PM","details":{"topic":"OD = Open Discussion meeting","interest":""}},"Sunday":{"start":"8:00 PM","end":"9:00 PM","details":{"topic":"OD = Open Discussion meeting","interest":""}}},"latlong":{"lat":"40.7927121","lng":"-73.94069"}},{"id":3,"meeting_name":"Harlem 1 Pm Recovery  Harlem 1 Pm Recovery","location_name":"Veterans Residence","meeting_address":"22 E 119TH ST New York NY ","meeting_times":{"Monday":{"start":"1:00 PM","end":"2:00 PM","details":{"topic":"B = Beginners meeting","interest":""}},"Tuesday":{"start":"","end":"","details":{"topic":"","interest":""}},"Wednesday":{"start":"","end":"","details":{"topic":"","interest":""}},"Thursday":{"start":"","end":"","details":{"topic":"","interest":""}},"Friday":{"start":"","end":"","details":{"topic":"","interest":""}},"Saturday":{"start":"","end":"","details":{"topic":"","interest":""}},"Sunday":{"start":"","end":"","details":{"topic":"","interest":""}}},"latlong":{"lat":"40.8021458","lng":"-73.9442327"}}]